pypolo/__init__.py
pypolo/dynamics/__init__.py
pypolo/dynamics/dubins_car.py
pypolo/dynamics/dynamics.py
pypolo/experiments/__init__.py
pypolo/experiments/argparser.py
pypolo/experiments/environments.py
pypolo/experiments/evaluator.py
pypolo/experiments/logger.py
pypolo/experiments/utilities.py
pypolo/experiments/visualizer.py
pypolo/kernels/__init__.py
pypolo/kernels/ak.py
pypolo/kernels/dkl.py
pypolo/kernels/gibbs.py
pypolo/kernels/kernel.py
pypolo/kernels/nn.py
pypolo/kernels/rbf.py
pypolo/kernels/scaler.py
pypolo/models/__init__.py
pypolo/models/gpr.py
pypolo/models/model.py
pypolo/objectives/__init__.py
pypolo/objectives/entropy.py
pypolo/robots/__init__.py
pypolo/robots/robot.py
pypolo/robots/usv.py
pypolo/sensors/__init__.py
pypolo/sensors/sensor.py
pypolo/sensors/sonar.py
pypolo/strategies/__init__.py
pypolo/strategies/active_sampling.py
pypolo/strategies/bezier.py
pypolo/strategies/myopic_planning.py
pypolo/strategies/random_sampling.py
pypolo/strategies/strategy.py
pypolo/utilities/__init__.py
pypolo/utilities/grid_map.py
pypolo/utilities/linalg.py
pypolo/utilities/scalers.py
pypolo-0.0.3.dist-info/LICENSE
pypolo-0.0.3.dist-info/METADATA
pypolo-0.0.3.dist-info/WHEEL
pypolo-0.0.3.dist-info/top_level.txt
pypolo-0.0.3.dist-info/RECORD
