Metadata-Version: 2.1
Name: pypolo
Version: 0.0.3
Summary: A Python Library for Informative Planning and Uncertainty-Aware Learning
Home-page: https://github.com/Weizhe-Chen/pypolo
Author: Weizhe (Wesley) Chen
Author-email: "Weizhe (Wesley) Chen" <wchen.robotics@outlook.com>
License: MIT License        
Project-URL: Homepage, https://pypolo.readthedocs.io
Project-URL: Bug Tracker, https://github.com/Weizhe-Chen/PyPolo/issues
Classifier: Programming Language :: Python :: 3
Classifier: License :: OSI Approved :: MIT License
Classifier: Operating System :: OS Independent
Requires-Python: >=3.6
License-File: LICENSE
Requires-Dist: torch (>=1.10)
Requires-Dist: matplotlib
Requires-Dist: bezier
Requires-Dist: scipy
Requires-Dist: configargparse
Requires-Dist: SciencePlots
Requires-Dist: tqdm
Requires-Dist: scikit-image
Provides-Extra: dev
Requires-Dist: yapf ; extra == 'dev'
Provides-Extra: docs
Requires-Dist: sphinx ; extra == 'docs'
Provides-Extra: examples
Requires-Dist: ipython ; extra == 'examples'
Requires-Dist: jupyter ; extra == 'examples'
Provides-Extra: test
Requires-Dist: pytest ; extra == 'test'
